cdopt/__init__.py
cdopt/core/__init__.py
cdopt/core/backbone_autograd.py
cdopt/core/backbone_jax.py
cdopt/core/backbone_torch.py
cdopt/core/problem.py
cdopt/core/problem_bak.py
cdopt/linen/__init__.py
cdopt/linen/linear.py
cdopt/manifold/__init__.py
cdopt/manifold/basic_manifold.py
cdopt/manifold/product_manifold.py
cdopt/manifold_jax/__init__.py
cdopt/manifold_jax/basic_manifold_jax.py
cdopt/manifold_jax/complex_oblique_jax.py
cdopt/manifold_jax/complex_sphere_jax.py
cdopt/manifold_jax/complex_stiefel_jax.py
cdopt/manifold_jax/euclidean_jax.py
cdopt/manifold_jax/generalized_stiefel_jax.py
cdopt/manifold_jax/grassmann_jax.py
cdopt/manifold_jax/hyperbolic_jax.py
cdopt/manifold_jax/oblique_jax.py
cdopt/manifold_jax/sphere_jax.py
cdopt/manifold_jax/stiefel_jax.py
cdopt/manifold_jax/stiefel_range_constraints_jax.py
cdopt/manifold_jax/symp_stiefel_jax.py
cdopt/manifold_np/__init__.py
cdopt/manifold_np/basic_manifold_np.py
cdopt/manifold_np/complex_oblique_np.py
cdopt/manifold_np/complex_sphere_np.py
cdopt/manifold_np/complex_stiefel_np.py
cdopt/manifold_np/euclidean_np.py
cdopt/manifold_np/generalized_stiefel_np.py
cdopt/manifold_np/grassmann_np.py
cdopt/manifold_np/hyperbolic_np.py
cdopt/manifold_np/oblique_np.py
cdopt/manifold_np/sphere_np.py
cdopt/manifold_np/stiefel_np.py
cdopt/manifold_np/stiefel_range_constraints_np.py
cdopt/manifold_np/symp_stiefel_np.py
cdopt/manifold_torch/__init__.py
cdopt/manifold_torch/basic_manifold_torch.py
cdopt/manifold_torch/complex_oblique_torch.py
cdopt/manifold_torch/complex_sphere_torch.py
cdopt/manifold_torch/complex_stiefel_torch.py
cdopt/manifold_torch/euclidean_torch.py
cdopt/manifold_torch/generalized_stiefel_torch.py
cdopt/manifold_torch/grassmann_torch.py
cdopt/manifold_torch/hyperbolic_torch.py
cdopt/manifold_torch/oblique_torch.py
cdopt/manifold_torch/sphere_torch.py
cdopt/manifold_torch/stiefel_range_constraint_torch.py
cdopt/manifold_torch/stiefel_torch.py
cdopt-0.5.5.dist-info/METADATA
cdopt-0.5.5.dist-info/RECORD
cdopt-0.5.5.dist-info/WHEEL
cdopt-0.5.5.dist-info/top_level.txt
