Metadata-Version: 2.1
Name: cdopt
Version: 0.5.5
Summary: A Python package for optimization on closed Riemannian manifolds
Home-page: https://cdopt.github.io/
Author: Nachuan Xiao, Xiaoyin Hu, Xin Liu, Kim-Chuan Toh
Author-email: xnc@lsec.cc.ac.cn
Keywords: Optimization,Riemannian optimization
Classifier: Programming Language :: Python :: 3
Classifier: Programming Language :: Python :: 3.7
Classifier: License :: OSI Approved :: BSD License
Classifier: Operating System :: OS Independent
Requires-Python: >=3.6
License-File: LICENSE
Requires-Dist: numpy (>=1.16)
Requires-Dist: scipy (>=1.7.0)
Requires-Dist: autograd
